{"stats":{"minecraft:used":{"minecraft:oak_fence":2,"minecraft:cherry_boat":6,"minecraft:cherry_sapling":27,"minecraft:iron_shovel":274,"minecraft:stone_shovel":543,"minecraft:oak_sign":3,"minecraft:chest":4,"minecraft:stone_hoe":815,"minecraft:oak_door":2,"minecraft:torch":73,"minecraft:dirt":436,"minecraft:hopper":5,"minecraft:carrot":700,"minecraft:oak_fence_gate":1,"minecraft:light_weighted_pressure_plate":3,"minecraft:cherry_button":2,"minecraft:furnace":1,"minecraft:egg":1,"minecraft:cherry_fence":112,"minecraft:potato":43,"minecraft:cooked_beef":30,"minecraft:red_dye":1,"minecraft:short_grass":71,"minecraft:wheat_seeds":8,"minecraft:water_bucket":37,"minecraft:cobblestone_stairs":5,"minecraft:stone_pickaxe":400,"minecraft:oak_planks":1,"minecraft:blue_bed":31,"minecraft:wooden_pickaxe":17,"minecraft:composter":13,"minecraft:cherry_planks":2,"minecraft:glow_ink_sac":2,"minecraft:cobblestone_slab":20,"minecraft:oak_leaves":57,"minecraft:white_wool":4,"minecraft:oak_slab":5,"minecraft:crafting_table":11,"minecraft:white_bed":7,"minecraft:dripstone_block":7,"minecraft:shears":168,"minecraft:cornflower":2,"minecraft:oak_log":1,"minecraft:yellow_dye":2,"minecraft:wooden_hoe":37,"minecraft:diamond_pickaxe":558,"minecraft:apple":4,"minecraft:oxeye_daisy":1,"minecraft:bread":40,"minecraft:iron_pickaxe":328,"minecraft:oak_button":2,"minecraft:iron_door":3,"minecraft:stone_axe":539,"minecraft:blue_carpet":15,"minecraft:cobblestone":637,"minecraft:cooked_porkchop":21,"minecraft:andesite":7,"minecraft:bucket":37,"minecraft:oak_boat":3,"minecraft:bone_meal":14},"minecraft:broken":{"minecraft:iron_shovel":1,"minecraft:shears":1,"minecraft:stone_hoe":6,"minecraft:stone_pickaxe":3,"minecraft:stone_axe":5,"minecraft:iron_pickaxe":1,"minecraft:wooden_hoe":1,"minecraft:stone_shovel":3},"minecraft:crafted":{"minecraft:cherry_planks":276,"minecraft:oak_door":3,"minecraft:oak_planks":168,"minecraft:cobblestone_slab":30,"minecraft:stone_shovel":4,"minecraft:furnace":1,"minecraft:cherry_boat":2,"minecraft:cobblestone_stairs":4,"minecraft:bone_meal":9,"minecraft:stone_pickaxe":3,"minecraft:chest":1,"minecraft:oak_button":2,"minecraft:iron_door":3,"minecraft:stone_hoe":6,"minecraft:oak_fence":3,"minecraft:cherry_fence":93,"minecraft:wheat":279,"minecraft:cherry_fence_gate":1,"minecraft:cooked_beef":30,"minecraft:red_dye":3,"minecraft:oak_slab":42,"minecraft:cooked_porkchop":34,"minecraft:crafting_table":5,"minecraft:wooden_pickaxe":1,"minecraft:cherry_button":2,"minecraft:blue_bed":28,"minecraft:stone_axe":6,"minecraft:bread":86,"minecraft:air":0,"minecraft:blue_dye":6,"minecraft:oak_fence_gate":1,"minecraft:oak_boat":1,"minecraft:yellow_dye":3,"minecraft:stick":140,"minecraft:iron_ingot":8,"minecraft:iron_pickaxe":1,"minecraft:iron_shovel":1,"minecraft:light_gray_dye":3,"minecraft:white_bed":2,"minecraft:composter":2,"minecraft:torch":64,"minecraft:shears":2,"minecraft:blue_carpet":12},"minecraft:killed":{"minecraft:spider":6,"minecraft:skeleton":3,"minecraft:bee":1,"minecraft:pig":18,"minecraft:iron_golem":4,"minecraft:creeper":4,"minecraft:sheep":7,"minecraft:zombie":18,"minecraft:glow_squid":1,"minecraft:enderman":1,"minecraft:cow":18},"minecraft:custom":{"minecraft:interact_with_smithing_table":1,"minecraft:mob_kills":83,"minecraft:animals_bred":28,"minecraft:inspect_hopper":4,"minecraft:interact_with_crafting_table":91,"minecraft:bell_ring":306,"minecraft:leave_game":17,"minecraft:time_since_death":306,"minecraft:climb_one_cm":352,"minecraft:sprint_one_cm":1726649,"minecraft:walk_one_cm":1951324,"minecraft:drop":589,"minecraft:talked_to_villager":51,"minecraft:play_time":526591,"minecraft:sneak_time":9976,"minecraft:deaths":36,"minecraft:walk_under_water_one_cm":1951,"minecraft:boat_one_cm":231148,"minecraft:interact_with_brewingstand":1,"minecraft:jump":6849,"minecraft:walk_on_water_one_cm":7142,"minecraft:total_world_time":526591,"minecraft:interact_with_furnace":16,"minecraft:interact_with_grindstone":2,"minecraft:sleep_in_bed":21,"minecraft:time_since_rest":364,"minecraft:damage_taken":15212,"minecraft:damage_dealt":17757,"minecraft:swim_one_cm":980,"minecraft:player_kills":3,"minecraft:fly_one_cm":1569175,"minecraft:open_chest":110,"minecraft:crouch_one_cm":42647,"minecraft:fall_one_cm":139825},"minecraft:picked_up":{"minecraft:crafting_table":7,"minecraft:wheat":19,"minecraft:azure_bluet":6,"minecraft:wooden_pickaxe":3,"minecraft:cornflower":11,"minecraft:string":9,"minecraft:iron_shovel":1,"minecraft:oak_sign":3,"minecraft:beetroot":8,"minecraft:cherry_boat":5,"minecraft:light_weighted_pressure_plate":3,"minecraft:beef":66,"minecraft:oak_boat":4,"minecraft:cobblestone_slab":26,"minecraft:poppy":8,"minecraft:iron_pickaxe":4,"minecraft:chest":5,"minecraft:iron_boots":2,"minecraft:egg":1,"minecraft:blue_wool":150,"minecraft:stick":62,"minecraft:raw_iron":6,"minecraft:oak_door":2,"minecraft:composter":7,"minecraft:oak_fence":3,"minecraft:torch":75,"minecraft:porkchop":76,"minecraft:cherry_log":69,"minecraft:pointed_dripstone":13,"minecraft:carrot":1328,"minecraft:blue_carpet":4,"minecraft:arrow":12,"minecraft:rotten_flesh":25,"minecraft:beetroot_seeds":23,"minecraft:shears":1,"minecraft:hay_block":39,"minecraft:mutton":29,"minecraft:white_wool":20,"minecraft:cobblestone":860,"minecraft:oxeye_daisy":6,"minecraft:cherry_planks":1,"minecraft:iron_door":2,"minecraft:glow_ink_sac":2,"minecraft:water_bucket":2,"minecraft:andesite":7,"minecraft:leather":63,"minecraft:potato":154,"minecraft:flint":10,"minecraft:oak_log":47,"minecraft:cherry_fence":19,"minecraft:gunpowder":6,"minecraft:cobblestone_stairs":15,"minecraft:dirt":708,"minecraft:blue_bed":3,"minecraft:bone":10,"minecraft:apple":52,"minecraft:wheat_seeds":248,"minecraft:iron_ingot":33,"minecraft:oak_planks":7,"minecraft:honeycomb":6,"minecraft:oak_slab":5,"minecraft:dandelion":50,"minecraft:dripstone_block":7,"minecraft:gravel":80,"minecraft:white_bed":7,"minecraft:stone_axe":3,"minecraft:short_grass":81,"minecraft:bone_meal":5,"minecraft:cherry_sapling":40,"minecraft:bread":27,"minecraft:emerald":8,"minecraft:oak_sapling":1,"minecraft:coal":33,"minecraft:oak_leaves":69,"minecraft:hopper":7,"minecraft:diamond_pickaxe":1},"minecraft:killed_by":{"minecraft:player":9,"minecraft:creeper":2,"minecraft:enderman":2,"minecraft:iron_golem":4,"minecraft:skeleton":9,"minecraft:zombie":3},"minecraft:mined":{"minecraft:blue_carpet":7,"minecraft:white_bed":7,"minecraft:farmland":9,"minecraft:oak_door":2,"minecraft:cobblestone_stairs":11,"minecraft:cherry_log":69,"minecraft:cherry_sapling":5,"minecraft:grass_block":317,"minecraft:composter":9,"minecraft:hopper":5,"minecraft:oak_wall_sign":3,"minecraft:oxeye_daisy":7,"minecraft:hay_block":38,"minecraft:tall_seagrass":1,"minecraft:carrots":348,"minecraft:fire":2,"minecraft:andesite":3,"minecraft:azure_bluet":3,"minecraft:potatoes":59,"minecraft:pointed_dripstone":3,"minecraft:dirt_path":15,"minecraft:cobblestone_slab":14,"minecraft:deepslate_iron_ore":6,"minecraft:stone":849,"minecraft:white_wool":2,"minecraft:cherry_planks":2,"minecraft:dandelion":36,"minecraft:oak_fence":2,"minecraft:cornflower":10,"minecraft:crafting_table":6,"minecraft:torch":24,"minecraft:short_grass":611,"minecraft:poppy":4,"minecraft:chest":3,"minecraft:copper_ore":2,"minecraft:tall_grass":119,"minecraft:cobblestone":149,"minecraft:oak_planks":6,"minecraft:blue_bed":3,"minecraft:iron_door":1,"minecraft:wall_torch":20,"minecraft:pink_petals":1,"minecraft:light_weighted_pressure_plate":3,"minecraft:cherry_fence":19,"minecraft:wheat":27,"minecraft:oak_log":44,"minecraft:coal_ore":22,"minecraft:beetroots":8,"minecraft:gravel":71,"minecraft:cherry_leaves":30,"minecraft:dirt":453,"minecraft:dripstone_block":11,"minecraft:oak_leaves":121},"minecraft:dropped":{"minecraft:iron_ingot":13,"minecraft:bread":65,"minecraft:short_grass":10,"minecraft:wheat_seeds":112,"minecraft:cobblestone":2,"minecraft:oxeye_daisy":2,"minecraft:dirt":225,"minecraft:torch":32,"minecraft:yellow_dye":1,"minecraft:cornflower":1,"minecraft:iron_door":2,"minecraft:red_dye":1,"minecraft:string":9,"minecraft:blue_carpet":1,"minecraft:dandelion":32,"minecraft:bone":1,"minecraft:gravel":40,"minecraft:stone_axe":3,"minecraft:wheat":3,"minecraft:pointed_dripstone":13,"minecraft:beetroot":8,"minecraft:rotten_flesh":19,"minecraft:oak_planks":1,"minecraft:azure_bluet":4,"minecraft:shears":1,"minecraft:carrot":634,"minecraft:poppy":3,"minecraft:cobblestone_slab":17,"minecraft:potato":73,"minecraft:gunpowder":4,"minecraft:beetroot_seeds":23,"minecraft:oak_boat":1,"minecraft:arrow":8,"minecraft:wooden_pickaxe":2,"minecraft:oak_leaves":12}},"DataVersion":3839}